[
  {
    "question": "Какая столица Франции?",
    "answer": "Париж",
    "level": 1,
    "answers": [
      "Париж",
      "Лондон",
      "Берлин",
      "Мадрид",
      "Рим",
      "Лиссабон"
    ]
  },
  {
    "question": "На каком континенте находится Египет?",
    "answer": "Африка",
    "level": 1,
    "answers": [
      "Африка",
      "Азия",
      "Европа",
      "Австралия",
      "Южная Америка",
      "Северная Америка"
    ]
  },
  {
    "question": "Какой океан самый большой?",
    "answer": "Тихий океан",
    "level": 1,
    "answers": [
      "Тихий океан",
      "Атлантический океан",
      "Индийский океан",
      "Северный Ледовитый океан",
      "Южный океан",
      "Средиземное море"
    ]
  },
  {
    "question": "В какой стране самое большое население?",
    "answer": "Китай",
    "level": 1,
    "answers": [
      "Китай",
      "Индия",
      "Соединенные Штаты",
      "Индонезия",
      "Россия",
      "Бразилия"
    ]
  },
  {
    "question": "Какая гора самая высокая в мире?",
    "answer": "Гора Эверест",
    "level": 1,
    "answers": [
      "Гора Эверест",
      "К2",
      "Канченджанга",
      "Лхоцзе",
      "Макалу",
      "Гора Килиманджаро"
    ]
  },
  {
    "question": "Какая столица Японии?",
    "answer": "Токио",
    "level": 1,
    "answers": [
      "Токио",
      "Сеул",
      "Пекин",
      "Бангкок",
      "Шанхай",
      "Осака"
    ]
  },
  {
    "question": "Какую страну называют Страной восходящего солнца?",
    "answer": "Япония",
    "level": 2,
    "answers": [
      "Япония",
      "Китай",
      "Южная Корея",
      "Таиланд",
      "Вьетнам",
      "Филиппины"
    ]
  },
  {
    "question": "Какая пустыня самая большая в мире?",
    "answer": "Сахара",
    "level": 2,
    "answers": [
      "Сахара",
      "Гоби",
      "Калахари",
      "Атакама",
      "арабский",
      "Великая Виктория"
    ]
  },
  {
    "question": "Какая страна имеет самую длинную береговую линию в мире?",
    "answer": "Канада",
    "level": 3,
    "answers": [
      "Канада",
      "Россия",
      "Австралия",
      "Соединенные Штаты",
      "Индонезия",
      "Норвегия"
    ]
  },
  {
    "question": "Какая страна в мире самая маленькая по площади?",
    "answer": "Ватикан",
    "level": 2,
    "answers": [
      "Ватикан",
      "Монако",
      "Сан-Марино",
      "Лихтенштейн",
      "Мальта",
      "Андорра"
    ]
  },
  {
    "question": "Какая река протекает через город Лондон?",
    "answer": "Темза",
    "level": 2,
    "answers": [
      "Темза",
      "Сена",
      "Дунай",
      "Рейн",
      "Волга",
      "Эльба"
    ]
  },
  {
    "question": "На каком континенте находится пустыня Сахара?",
    "answer": "Африка",
    "level": 2,
    "answers": [
      "Африка",
      "Азия",
      "Северная Америка",
      "Австралия",
      "Европа",
      "Южная Америка"
    ]
  },
  {
    "question": "Какой остров самый большой в мире?",
    "answer": "Гренландия",
    "level": 1,
    "answers": [
      "Гренландия",
      "Новая Гвинея",
      "Борнео",
      "Мадагаскар",
      "Великобритания",
      "Суматра"
    ]
  },
  {
    "question": "В какой стране находится Большой Барьерный риф?",
    "answer": "Австралия",
    "level": 2,
    "answers": [
      "Австралия",
      "Новая Зеландия",
      "Фиджи",
      "Индонезия",
      "Филиппины",
      "Малайзия"
    ]
  },
  {
    "question": "В каком штате США находится Гранд-Каньон?",
    "answer": "Аризона",
    "level": 3,
    "answers": [
      "Аризона",
      "Калифорния",
      "Невада",
      "Юта",
      "Нью-Мексико",
      "Колорадо"
    ]
  },
  {
    "question": "В какой стране больше всего часовых поясов?",
    "answer": "Франция",
    "level": 3,
    "answers": [
      "Франция",
      "Россия",
      "Соединенные Штаты",
      "Китай",
      "Канада",
      "Бразилия"
    ]
  },
  {
    "question": "Какая столица Австралии?",
    "answer": "Канберра",
    "level": 2,
    "answers": [
      "Канберра",
      "Сидней",
      "Мельбурн",
      "Брисбен",
      "Перт",
      "Аделаида"
    ]
  },
  {
    "question": "На каком континенте находится страна Бразилия?",
    "answer": "Южная Америка",
    "level": 1,
    "answers": [
      "Южная Америка",
      "Северная Америка",
      "Европа",
      "Африка",
      "Азия",
      "Австралия"
    ]
  },
  {
    "question": "Какая самая высокая гора в Африке?",
    "answer": "Гора Килиманджаро",
    "level": 2,
    "answers": [
      "Гора Килиманджаро",
      "Гора Кения",
      "Атласские горы",
      "Рас Дашен",
      "Горы Сымен",
      "Горы Рувензори"
    ]
  },
  {
    "question": "Какое море разделяет Европу и Африку?",
    "answer": "Средиземное море",
    "level": 2,
    "answers": [
      "Средиземное море",
      "Красное море",
      "Черное море",
      "Каспийское море",
      "Адриатическое море",
      "Эгейское море"
    ]
  },
  {
    "question": "Какая самая большая страна Южной Америки?",
    "answer": "Бразилия",
    "level": 2,
    "answers": [
      "Бразилия",
      "Аргентина",
      "Колумбия",
      "Перу",
      "Чили",
      "Венесуэла"
    ]
  },
  {
    "question": "Какой штат США является самым большим по площади?",
    "answer": "Аляска",
    "level": 2,
    "answers": [
      "Аляска",
      "Техас",
      "Калифорния",
      "Монтана",
      "Нью-Мексико",
      "Невада"
    ]
  },
  {
    "question": "Какая столица Канады?",
    "answer": "Оттава",
    "level": 1,
    "answers": [
      "Оттава",
      "Торонто",
      "Ванкувер",
      "Монреаль",
      "Калгари",
      "Эдмонтон"
    ]
  },
  {
    "question": "Какая страна имеет самую длинную границу с США?",
    "answer": "Канада",
    "level": 1,
    "answers": [
      "Канада",
      "Мексика",
      "Россия",
      "Куба",
      "Гренландия",
      "Багамы"
    ]
  },
  {
    "question": "Какая столица России?",
    "answer": "Москва",
    "level": 1,
    "answers": [
      "Москва",
      "Санкт-Петербург",
      "Киев",
      "Минск",
      "Владивосток",
      "Новосибирск"
    ]
  },
  {
    "question": "На каком континенте больше всего стран?",
    "answer": "Африка",
    "level": 2,
    "answers": [
      "Африка",
      "Азия",
      "Европа",
      "Северная Америка",
      "Южная Америка",
      "Австралия"
    ]
  },
  {
    "question": "Какая европейская страна известна своими фьордами?",
    "answer": "Норвегия",
    "level": 2,
    "answers": [
      "Норвегия",
      "Швеция",
      "Финляндия",
      "Исландия",
      "Дания",
      "Шотландия"
    ]
  },
  {
    "question": "Какая самая длинная река в Европе?",
    "answer": "Волга",
    "level": 3,
    "answers": [
      "Волга",
      "Дунай",
      "Рейн",
      "Сена",
      "Днепр",
      "Луара"
    ]
  },
  {
    "question": "Какой океан в мире самый маленький?",
    "answer": "Северный Ледовитый океан",
    "level": 2,
    "answers": [
      "Северный Ледовитый океан",
      "Индийский океан",
      "Южный океан",
      "Тихий океан",
      "Атлантический океан",
      "Средиземное море"
    ]
  },
  {
    "question": "Какая столица Италии?",
    "answer": "Рим",
    "level": 1,
    "answers": [
      "Рим",
      "Милан",
      "Венеция",
      "Флоренция",
      "Неаполь",
      "Турин"
    ]
  },
  {
    "question": "Какой официальный язык Бразилии?",
    "answer": "португальский",
    "level": 2,
    "answers": [
      "португальский",
      "испанский",
      "Английский",
      "Французский",
      "немецкий",
      "итальянский"
    ]
  },
  {
    "question": "Какая страна является самой большой в мире по площади?",
    "answer": "Россия",
    "level": 1,
    "answers": [
      "Россия",
      "Канада",
      "Китай",
      "Соединенные Штаты",
      "Бразилия",
      "Австралия"
    ]
  },
  {
    "question": "Какое море находится между Австралией и Новой Зеландией?",
    "answer": "Тасманово море",
    "level": 4,
    "answers": [
      "Тасманово море",
      "Коралловое море",
      "Арафурское море",
      "Море Бисмарка",
      "Тиморское море",
      "Яванское море"
    ]
  },
  {
    "question": "Какой континент самый засушливый?",
    "answer": "Антарктида",
    "level": 2,
    "answers": [
      "Антарктида",
      "Африка",
      "Австралия",
      "Азия",
      "Европа",
      "Южная Америка"
    ]
  },
  {
    "question": "Какая пустыня в мире самая большая?",
    "answer": "Антарктическая пустыня",
    "level": 2,
    "answers": [
      "Антарктическая пустыня",
      "Пустыня Сахара",
      "Пустыня Гоби",
      "Аравийская пустыня",
      "Пустыня Калахари",
      "Пустыня Атакама"
    ]
  },
  {
    "question": "Какую страну называют страной тысячи озер?",
    "answer": "Финляндия",
    "level": 3,
    "answers": [
      "Финляндия",
      "Швеция",
      "Норвегия",
      "Канада",
      "Исландия",
      "Россия"
    ]
  },
  {
    "question": "На каком материке расположены горы Анды?",
    "answer": "Южная Америка",
    "level": 2,
    "answers": [
      "Южная Америка",
      "Северная Америка",
      "Африка",
      "Европа",
      "Азия",
      "Австралия"
    ]
  },
  {
    "question": "Какое пресноводное озеро самое большое по площади?",
    "answer": "Озеро Верхнее",
    "level": 3,
    "answers": [
      "Озеро Верхнее",
      "Озеро Виктория",
      "Озеро Мичиган",
      "Озеро Гурон",
      "Каспийское море",
      "Озеро Байкал"
    ]
  },
  {
    "question": "Какая столица Германии?",
    "answer": "Берлин",
    "level": 1,
    "answers": [
      "Берлин",
      "Мюнхен",
      "Гамбург",
      "Франкфурт",
      "Штутгарт",
      "Кёльн"
    ]
  },
  {
    "question": "В какой стране находится гора Фудзи?",
    "answer": "Япония",
    "level": 2,
    "answers": [
      "Япония",
      "Китай",
      "Южная Корея",
      "Индонезия",
      "Филиппины",
      "Вьетнам"
    ]
  },
  {
    "question": "Какая столица Испании?",
    "answer": "Мадрид",
    "level": 1,
    "answers": [
      "Мадрид",
      "Барселона",
      "Валенсия",
      "Севилья",
      "Малага",
      "Бильбао"
    ]
  },
  {
    "question": "Какая африканская страна является самой большой по площади?",
    "answer": "Алжир",
    "level": 3,
    "answers": [
      "Алжир",
      "Судан",
      "Конго",
      "ЮАР",
      "Нигерия",
      "Египет"
    ]
  },
  {
    "question": "Какую страну называют жемчужиной Индийского океана?",
    "answer": "Шри-Ланка",
    "level": 3,
    "answers": [
      "Шри-Ланка",
      "Мальдивы",
      "Индия",
      "Индонезия",
      "Таиланд",
      "Малайзия"
    ]
  },
  {
    "question": "Какая столица Египта?",
    "answer": "Каир",
    "level": 2,
    "answers": [
      "Каир",
      "Александрия",
      "Луксор",
      "Гиза",
      "Асуан",
      "Порт-Саид"
    ]
  },
  {
    "question": "Какая самая длинная река в Северной Америке?",
    "answer": "Река Миссисипи",
    "level": 3,
    "answers": [
      "Река Миссисипи",
      "Река Миссури",
      "Река Юкон",
      "Река Колорадо",
      "Рио-Гранде",
      "Река Огайо"
    ]
  },
  {
    "question": "Какая столица Индии?",
    "answer": "Нью-Дели",
    "level": 1,
    "answers": [
      "Нью-Дели",
      "Мумбаи",
      "Бангалор",
      "Калькутта",
      "Ченнаи",
      "Хайдарабад"
    ]
  },
  {
    "question": "В какой стране Африки самое большое население?",
    "answer": "Нигерия",
    "level": 3,
    "answers": [
      "Нигерия",
      "Эфиопия",
      "Египет",
      "ЮАР",
      "Кения",
      "Демократическая Республика Конго"
    ]
  },
  {
    "question": "На каком континенте нет пустыни?",
    "answer": "Европа",
    "level": 2,
    "answers": [
      "Европа",
      "Азия",
      "Северная Америка",
      "Южная Америка",
      "Австралия",
      "Африка"
    ]
  },
  {
    "question": "В какой стране больше всего объектов Всемирного наследия ЮНЕСКО?",
    "answer": "Италия",
    "level": 3,
    "answers": [
      "Италия",
      "Китай",
      "Испания",
      "Германия",
      "Франция",
      "Индия"
    ]
  },
  {
    "question": "Какая самая глубокая точка мирового океана?",
    "answer": "Марианская впадина",
    "level": 3,
    "answers": [
      "Марианская впадина",
      "Тонга желоб",
      "Яванский желоб",
      "Пуэрто-Рико Тренч",
      "Филиппинский желоб",
      "Кермадекский желоб"
    ]
  },
  {
    "question": "Какая европейская страна имеет самую длинную береговую линию?",
    "answer": "Норвегия",
    "level": 4,
    "answers": [
      "Норвегия",
      "Греция",
      "Италия",
      "Испания",
      "Великобритания",
      "Швеция"
    ]
  },
  {
    "question": "Какая горная система является самой длинной в мире?",
    "answer": "Анды",
    "level": 4,
    "answers": [
      "Анды",
      "Скалистые горы",
      "Гималаи",
      "Альпы",
      "Большой разделительный диапазон",
      "Атласские горы"
    ]
  },
  {
    "question": "Какая единственная страна граничит с Великобританией?",
    "answer": "Ирландия",
    "level": 3,
    "answers": [
      "Ирландия",
      "Франция",
      "Бельгия",
      "Нидерланды",
      "Дания",
      "Германия"
    ]
  },
  {
    "question": "Какая река образует естественную границу между США и Мексикой?",
    "answer": "Рио-Гранде",
    "level": 4,
    "answers": [
      "Рио-Гранде",
      "Река Колорадо",
      "Река Миссисипи",
      "Река Юкон",
      "Река Колумбия",
      "Река Арканзас"
    ]
  },
  {
    "question": "Какая пустыня покрывает большую часть северного Китая и южной Монголии?",
    "answer": "Пустыня Гоби",
    "level": 4,
    "answers": [
      "Пустыня Гоби",
      "Пустыня Такла-Макан",
      "Пустыня Каракумы",
      "Пустыня Тар",
      "Пустыня Сонора",
      "Пустыня Кызылкум"
    ]
  },
  {
    "question": "Какая гора вторая по высоте в мире?",
    "answer": "К2",
    "level": 3,
    "answers": [
      "К2",
      "Гора Эверест",
      "Канченджанга",
      "Лхоцзе",
      "Макалу",
      "Чо Ойю"
    ]
  },
  {
    "question": "Какая столица Казахстана?",
    "answer": "Астана",
    "level": 3,
    "answers": [
      "Астана",
      "Алматы",
      "Бишкек",
      "Ташкент",
      "Душанбе",
      "Ашхабад"
    ]
  },
  {
    "question": "Какая страна контролирует Галапагосские острова?",
    "answer": "Эквадор",
    "level": 4,
    "answers": [
      "Эквадор",
      "Перу",
      "Колумбия",
      "Чили",
      "Аргентина",
      "Бразилия"
    ]
  },
  {
    "question": "Какая столица Мексики?",
    "answer": "Мехико",
    "level": 2,
    "answers": [
      "Мехико",
      "Гвадалахара",
      "Монтеррей",
      "Тихуана",
      "Канкун",
      "Пуэбла"
    ]
  },
  {
    "question": "На каком континенте находится Австралия?",
    "answer": "Австралия",
    "level": 1,
    "answers": [
      "Австралия",
      "Азия",
      "Африка",
      "Европа",
      "Южная Америка",
      "Северная Америка"
    ]
  },
  {
    "question": "Какая страна знаменита Эйфелевой башней?",
    "answer": "Франция",
    "level": 1,
    "answers": [
      "Франция",
      "Италия",
      "Германия",
      "Испания",
      "Великобритания",
      "Бельгия"
    ]
  },
  {
    "question": "На каком континенте находится страна Индия?",
    "answer": "Азия",
    "level": 1,
    "answers": [
      "Азия",
      "Африка",
      "Европа",
      "Северная Америка",
      "Южная Америка",
      "Австралия"
    ]
  },
  {
    "question": "Какой океан расположен к западу от США?",
    "answer": "Тихий океан",
    "level": 2,
    "answers": [
      "Тихий океан",
      "Атлантический океан",
      "Индийский океан",
      "Северный Ледовитый океан",
      "Южный океан",
      "Средиземное море"
    ]
  },
  {
    "question": "Какую страну называют Страной кленового листа?",
    "answer": "Канада",
    "level": 1,
    "answers": [
      "Канада",
      "Соединенные Штаты",
      "Великобритания",
      "Австралия",
      "Новая Зеландия",
      "Швеция"
    ]
  },
  {
    "question": "Какая столица Китая?",
    "answer": "Пекин",
    "level": 1,
    "answers": [
      "Пекин",
      "Шанхай",
      "Гонконг",
      "Гуанчжоу",
      "Чэнду",
      "Шэньчжэнь"
    ]
  },
  {
    "question": "Какой континент является самым большим по площади?",
    "answer": "Азия",
    "level": 2,
    "answers": [
      "Азия",
      "Африка",
      "Северная Америка",
      "Европа",
      "Австралия",
      "Южная Америка"
    ]
  },
  {
    "question": "Какая страна славится пиццей и пастой?",
    "answer": "Италия",
    "level": 1,
    "answers": [
      "Италия",
      "Франция",
      "Испания",
      "Мексика",
      "Греция",
      "Германия"
    ]
  },
  {
    "question": "Какая столица Аргентины?",
    "answer": "Буэнос-Айрес",
    "level": 1,
    "answers": [
      "Буэнос-Айрес",
      "Лима",
      "Сантьяго",
      "Монтевидео",
      "Асунсьон",
      "Бразилиа"
    ]
  },
  {
    "question": "Какая пустыня является самой большой жаркой пустыней в мире?",
    "answer": "Сахара",
    "level": 2,
    "answers": [
      "Сахара",
      "Гоби",
      "Калахари",
      "арабский",
      "Атакама",
      "Сонора"
    ]
  },
  {
    "question": "В какой стране находится город Сидней?",
    "answer": "Австралия",
    "level": 1,
    "answers": [
      "Австралия",
      "Новая Зеландия",
      "Канада",
      "Соединенные Штаты",
      "ЮАР",
      "Великобритания"
    ]
  },
  {
    "question": "Какой штат США называют солнечным штатом?",
    "answer": "Флорида",
    "level": 3,
    "answers": [
      "Флорида",
      "Калифорния",
      "Техас",
      "Аризона",
      "Гавайи",
      "Невада"
    ]
  },
  {
    "question": "Какая столица Южной Кореи?",
    "answer": "Сеул",
    "level": 1,
    "answers": [
      "Сеул",
      "Пусан",
      "Инчхон",
      "Тэгу",
      "Кванджу",
      "Тэджон"
    ]
  },
  {
    "question": "Какой горный массив расположен между Францией и Испанией?",
    "answer": "Пиренеи",
    "level": 3,
    "answers": [
      "Пиренеи",
      "Альпы",
      "Скалистые горы",
      "Гималаи",
      "Карпаты",
      "Анды"
    ]
  },
  {
    "question": "Какая столица Таиланда?",
    "answer": "Бангкок",
    "level": 1,
    "answers": [
      "Бангкок",
      "Пхукет",
      "Чиангмай",
      "Паттайя",
      "Краби",
      "Аютия"
    ]
  },
  {
    "question": "us.png",
    "answer": "Соединенные Штаты",
    "isImg": true,
    "answers": [
      "Соединенные Штаты",
      "Канада",
      "Мексика",
      "Великобритания",
      "Австралия",
      "Новая Зеландия"
    ],
    "level": 1
  },
  {
    "question": "fr.png",
    "answer": "Франция",
    "isImg": true,
    "answers": [
      "Франция",
      "Германия",
      "Италия",
      "Испания",
      "Бельгия",
      "Швейцария"
    ],
    "level": 1
  },
  {
    "question": "de.png",
    "answer": "Германия",
    "isImg": true,
    "answers": [
      "Германия",
      "Австрия",
      "Швейцария",
      "Бельгия",
      "Нидерланды",
      "Дания"
    ],
    "level": 1
  },
  {
    "question": "es.png",
    "answer": "Испания",
    "isImg": true,
    "answers": [
      "Испания",
      "Португалия",
      "Италия",
      "Франция",
      "Мексика",
      "Аргентина"
    ],
    "level": 1
  },
  {
    "question": "it.png",
    "answer": "Италия",
    "isImg": true,
    "answers": [
      "Италия",
      "Франция",
      "Испания",
      "Португалия",
      "Греция",
      "Швейцария"
    ],
    "level": 1
  },
  {
    "question": "cn.png",
    "answer": "Китай",
    "isImg": true,
    "answers": [
      "Китай",
      "Япония",
      "Южная Корея",
      "Вьетнам",
      "Таиланд",
      "Тайвань"
    ],
    "level": 1
  },
  {
    "question": "jp.png",
    "answer": "Япония",
    "isImg": true,
    "answers": [
      "Япония",
      "Южная Корея",
      "Китай",
      "Таиланд",
      "Филиппины",
      "Вьетнам"
    ],
    "level": 1
  },
  {
    "question": "ca.png",
    "answer": "Канада",
    "isImg": true,
    "answers": [
      "Канада",
      "Соединенные Штаты",
      "Австралия",
      "Новая Зеландия",
      "Великобритания",
      "Ирландия"
    ],
    "level": 1
  },
  {
    "question": "br.png",
    "answer": "Бразилия",
    "isImg": true,
    "answers": [
      "Бразилия",
      "Аргентина",
      "Мексика",
      "Чили",
      "Колумбия",
      "Перу"
    ],
    "level": 1
  },
  {
    "question": "gb.png",
    "answer": "Великобритания",
    "isImg": true,
    "answers": [
      "Великобритания",
      "Ирландия",
      "Австралия",
      "Новая Зеландия",
      "Канада",
      "Соединенные Штаты"
    ],
    "level": 1
  },
  {
    "question": "au.png",
    "answer": "Австралия",
    "isImg": true,
    "answers": [
      "Австралия",
      "Новая Зеландия",
      "Канада",
      "Соединенные Штаты",
      "Великобритания",
      "ЮАР"
    ],
    "level": 1
  },
  {
    "question": "ru.png",
    "answer": "Россия",
    "isImg": true,
    "answers": [
      "Россия",
      "Украина",
      "Беларусь",
      "Казахстан",
      "Польша",
      "Литва"
    ],
    "level": 2
  },
  {
    "question": "in.png",
    "answer": "Индия",
    "isImg": true,
    "answers": [
      "Индия",
      "Пакистан",
      "Шри-Ланка",
      "Непал",
      "Бангладеш",
      "Бутан"
    ],
    "level": 1
  },
  {
    "question": "mx.png",
    "answer": "Мексика",
    "isImg": true,
    "answers": [
      "Мексика",
      "Аргентина",
      "Испания",
      "Бразилия",
      "Колумбия",
      "Чили"
    ],
    "level": 1
  },
  {
    "question": "za.png",
    "answer": "ЮАР",
    "isImg": true,
    "answers": [
      "ЮАР",
      "Зимбабве",
      "Намибия",
      "Ботсвана",
      "Лесото",
      "Эсватини"
    ],
    "level": 2
  },
  {
    "question": "eg.png",
    "answer": "Египет",
    "isImg": true,
    "answers": [
      "Египет",
      "Судан",
      "Ливия",
      "Алжир",
      "Марокко",
      "Тунис"
    ],
    "level": 2
  },
  {
    "question": "kr.png",
    "answer": "Южная Корея",
    "isImg": true,
    "answers": [
      "Южная Корея",
      "Япония",
      "Китай",
      "Вьетнам",
      "Филиппины",
      "Таиланд"
    ],
    "level": 1
  },
  {
    "question": "ar.png",
    "answer": "Аргентина",
    "isImg": true,
    "answers": [
      "Аргентина",
      "Бразилия",
      "Чили",
      "Уругвай",
      "Парагвай",
      "Мексика"
    ],
    "level": 1
  },
  {
    "question": "se.png",
    "answer": "Швеция",
    "isImg": true,
    "answers": [
      "Швеция",
      "Норвегия",
      "Дания",
      "Финляндия",
      "Исландия",
      "Германия"
    ],
    "level": 2
  },
  {
    "question": "pl.png",
    "answer": "Польша",
    "isImg": true,
    "answers": [
      "Польша",
      "Чешская Республика",
      "Словакия",
      "Венгрия",
      "Германия",
      "Украина"
    ],
    "level": 1
  },
  {
    "question": "nl.png",
    "answer": "Нидерланды",
    "isImg": true,
    "answers": [
      "Нидерланды",
      "Бельгия",
      "Германия",
      "Франция",
      "Люксембург",
      "Дания"
    ],
    "level": 1
  },
  {
    "question": "ch.png",
    "answer": "Швейцария",
    "isImg": true,
    "answers": [
      "Швейцария",
      "Австрия",
      "Германия",
      "Франция",
      "Италия",
      "Бельгия"
    ],
    "level": 2
  },
  {
    "question": "no.png",
    "answer": "Норвегия",
    "isImg": true,
    "answers": [
      "Норвегия",
      "Швеция",
      "Дания",
      "Финляндия",
      "Исландия",
      "Гренландия"
    ],
    "level": 2
  },
  {
    "question": "gr.png",
    "answer": "Греция",
    "isImg": true,
    "answers": [
      "Греция",
      "Италия",
      "Кипр",
      "Турция",
      "Албания",
      "Болгария"
    ],
    "level": 2
  },
  {
    "question": "pt.png",
    "answer": "Португалия",
    "isImg": true,
    "answers": [
      "Португалия",
      "Испания",
      "Италия",
      "Бразилия",
      "Аргентина",
      "Франция"
    ],
    "level": 1
  },
  {
    "question": "ua.png",
    "answer": "Украина",
    "isImg": true,
    "answers": [
      "Украина",
      "Россия",
      "Беларусь",
      "Польша",
      "Молдова",
      "Румыния"
    ],
    "level": 2
  },
  {
    "question": "dk.png",
    "answer": "Дания",
    "isImg": true,
    "answers": [
      "Дания",
      "Швеция",
      "Норвегия",
      "Финляндия",
      "Германия",
      "Нидерланды"
    ],
    "level": 2
  },
  {
    "question": "tr.png",
    "answer": "Турция",
    "isImg": true,
    "answers": [
      "Турция",
      "Греция",
      "Кипр",
      "Армения",
      "Иран",
      "Азербайджан"
    ],
    "level": 2
  },
  {
    "question": "nz.png",
    "answer": "Новая Зеландия",
    "isImg": true,
    "answers": [
      "Новая Зеландия",
      "Австралия",
      "Канада",
      "ЮАР",
      "Великобритания",
      "Фиджи"
    ],
    "level": 1
  },
  {
    "question": "fi.png",
    "answer": "Финляндия",
    "isImg": true,
    "answers": [
      "Финляндия",
      "Швеция",
      "Норвегия",
      "Дания",
      "Эстония",
      "Россия"
    ],
    "level": 2
  },
  {
    "question": "at.png",
    "answer": "Австрия",
    "isImg": true,
    "answers": [
      "Австрия",
      "Швейцария",
      "Германия",
      "Венгрия",
      "Чешская Республика",
      "Словакия"
    ],
    "level": 2
  },
  {
    "question": "hu.png",
    "answer": "Венгрия",
    "isImg": true,
    "answers": [
      "Венгрия",
      "Австрия",
      "Словакия",
      "Румыния",
      "Сербия",
      "Хорватия"
    ],
    "level": 2
  },
  {
    "question": "cz.png",
    "answer": "Чешская Республика",
    "isImg": true,
    "answers": [
      "Чешская Республика",
      "Словакия",
      "Польша",
      "Германия",
      "Австрия",
      "Венгрия"
    ],
    "level": 2
  },
  {
    "question": "ie.png",
    "answer": "Ирландия",
    "isImg": true,
    "answers": [
      "Ирландия",
      "Великобритания",
      "Шотландия",
      "Уэльс",
      "Северная Ирландия",
      "Исландия"
    ],
    "level": 2
  },
  {
    "question": "is.png",
    "answer": "Исландия",
    "isImg": true,
    "answers": [
      "Исландия",
      "Гренландия",
      "Норвегия",
      "Дания",
      "Финляндия",
      "Швеция"
    ],
    "level": 3
  },
  {
    "question": "cl.png",
    "answer": "Чили",
    "isImg": true,
    "answers": [
      "Чили",
      "Аргентина",
      "Перу",
      "Уругвай",
      "Бразилия",
      "Колумбия"
    ],
    "level": 2
  },
  {
    "question": "vn.png",
    "answer": "Вьетнам",
    "isImg": true,
    "answers": [
      "Вьетнам",
      "Таиланд",
      "Камбоджа",
      "Лаос",
      "Малайзия",
      "Филиппины"
    ],
    "level": 2
  },
  {
    "question": "th.png",
    "answer": "Таиланд",
    "isImg": true,
    "answers": [
      "Таиланд",
      "Вьетнам",
      "Малайзия",
      "Индонезия",
      "Камбоджа",
      "Мьянма"
    ],
    "level": 2
  },
  {
    "question": "il.png",
    "answer": "Израиль",
    "isImg": true,
    "answers": [
      "Израиль",
      "Ливан",
      "Иордания",
      "Сирия",
      "Египет",
      "Палестина"
    ],
    "level": 2
  },
  {
    "question": "ng.png",
    "answer": "Нигерия",
    "isImg": true,
    "answers": [
      "Нигерия",
      "Гана",
      "Камерун",
      "Чад",
      "Сенегал",
      "Кот-д'Ивуар"
    ],
    "level": 2
  },
  {
    "question": "ph.png",
    "answer": "Филиппины",
    "isImg": true,
    "answers": [
      "Филиппины",
      "Вьетнам",
      "Индонезия",
      "Таиланд",
      "Малайзия",
      "Сингапур"
    ],
    "level": 2
  },
  {
    "question": "pk.png",
    "answer": "Пакистан",
    "isImg": true,
    "answers": [
      "Пакистан",
      "Индия",
      "Бангладеш",
      "Афганистан",
      "Шри-Ланка",
      "Непал"
    ],
    "level": 2
  },
  {
    "question": "pt.png",
    "answer": "Португалия",
    "isImg": true,
    "answers": [
      "Португалия",
      "Испания",
      "Бразилия",
      "Италия",
      "Франция",
      "Аргентина"
    ],
    "level": 1
  },
  {
    "question": "ae.png",
    "answer": "Объединенные Арабские Эмираты",
    "isImg": true,
    "answers": [
      "Объединенные Арабские Эмираты",
      "Саудовская Аравия",
      "Катар",
      "Бахрейн",
      "Кувейт",
      "Оман"
    ],
    "level": 2
  },
  {
    "question": "lk.png",
    "answer": "Шри-Ланка",
    "isImg": true,
    "answers": [
      "Шри-Ланка",
      "Индия",
      "Бангладеш",
      "Мальдивы",
      "Пакистан",
      "Непал"
    ],
    "level": 2
  },
  {
    "question": "sa.png",
    "answer": "Саудовская Аравия",
    "isImg": true,
    "answers": [
      "Саудовская Аравия",
      "Катар",
      "Объединенные Арабские Эмираты",
      "Кувейт",
      "Оман",
      "Бахрейн"
    ],
    "level": 2
  },
  {
    "question": "kz.png",
    "answer": "Казахстан",
    "isImg": true,
    "answers": [
      "Казахстан",
      "Узбекистан",
      "Туркменистан",
      "Кыргызстан",
      "Россия",
      "Монголия"
    ],
    "level": 3
  },
  {
    "question": "ke.png",
    "answer": "Кения",
    "isImg": true,
    "answers": [
      "Кения",
      "Уганда",
      "Танзания",
      "Руанда",
      "Эфиопия",
      "Судан"
    ],
    "level": 2
  },
  {
    "question": "my.png",
    "answer": "Малайзия",
    "isImg": true,
    "answers": [
      "Малайзия",
      "Индонезия",
      "Сингапур",
      "Таиланд",
      "Вьетнам",
      "Филиппины"
    ],
    "level": 2
  },
  {
    "question": "dz.png",
    "answer": "Алжир",
    "isImg": true,
    "answers": [
      "Алжир",
      "Марокко",
      "Тунис",
      "Ливия",
      "Египет",
      "Мавритания"
    ],
    "level": 2
  },
  {
    "question": "ge.png",
    "answer": "Грузия",
    "isImg": true,
    "answers": [
      "Грузия",
      "Армения",
      "Азербайджан",
      "Турция",
      "Россия",
      "Украина"
    ],
    "level": 3
  },
  {
    "question": "jo.png",
    "answer": "Иордания",
    "isImg": true,
    "answers": [
      "Иордания",
      "Израиль",
      "Ливан",
      "Сирия",
      "Египет",
      "Палестина"
    ],
    "level": 2
  },
  {
    "question": "ec.png",
    "answer": "Эквадор",
    "isImg": true,
    "answers": [
      "Эквадор",
      "Перу",
      "Колумбия",
      "Чили",
      "Аргентина",
      "Венесуэла"
    ],
    "level": 2
  },
  {
    "question": "bg.png",
    "answer": "Болгария",
    "isImg": true,
    "answers": [
      "Болгария",
      "Румыния",
      "Сербия",
      "Греция",
      "Турция",
      "Северная Македония"
    ],
    "level": 3
  },
  {
    "question": "vn.png",
    "answer": "Вьетнам",
    "isImg": true,
    "answers": [
      "Вьетнам",
      "Камбоджа",
      "Таиланд",
      "Малайзия",
      "Лаос",
      "Филиппины"
    ],
    "level": 2
  },
  {
    "question": "bd.png",
    "answer": "Бангладеш",
    "isImg": true,
    "answers": [
      "Бангладеш",
      "Индия",
      "Пакистан",
      "Непал",
      "Мьянма",
      "Шри-Ланка"
    ],
    "level": 2
  },
  {
    "question": "mt.png",
    "answer": "Мальта",
    "isImg": true,
    "answers": [
      "Мальта",
      "Кипр",
      "Греция",
      "Италия",
      "Испания",
      "Португалия"
    ],
    "level": 3
  },
  {
    "question": "lk.png",
    "answer": "Шри-Ланка",
    "isImg": true,
    "answers": [
      "Шри-Ланка",
      "Индия",
      "Мальдивы",
      "Бангладеш",
      "Пакистан",
      "Непал"
    ],
    "level": 2
  },
  {
    "question": "bt.png",
    "answer": "Бутан",
    "isImg": true,
    "answers": [
      "Бутан",
      "Непал",
      "Тибет",
      "Бангладеш",
      "Шри-Ланка",
      "Мьянма"
    ],
    "level": 4
  },
  {
    "question": "cv.png",
    "answer": "Кабо-Верде",
    "isImg": true,
    "answers": [
      "Кабо-Верде",
      "Сейшельские острова",
      "Маврикий",
      "Коморские острова",
      "Мадагаскар",
      "Габон"
    ],
    "level": 4
  },
  {
    "question": "tl.png",
    "answer": "Тимор-Лешти",
    "isImg": true,
    "answers": [
      "Тимор-Лешти",
      "Индонезия",
      "Малайзия",
      "Папуа-Новая Гвинея",
      "Бруней",
      "Филиппины"
    ],
    "level": 4
  },
  {
    "question": "dj.png",
    "answer": "Джибути",
    "isImg": true,
    "answers": [
      "Джибути",
      "Эритрея",
      "Сомали",
      "Эфиопия",
      "Судан",
      "Йемен"
    ],
    "level": 4
  },
  {
    "question": "gq.png",
    "answer": "Экваториальная Гвинея",
    "isImg": true,
    "answers": [
      "Экваториальная Гвинея",
      "Габон",
      "Камерун",
      "Конго",
      "Ангола",
      "Гвинея"
    ],
    "level": 4
  },
  {
    "question": "bi.png",
    "answer": "Бурунди",
    "isImg": true,
    "answers": [
      "Бурунди",
      "Руанда",
      "Уганда",
      "Танзания",
      "Кения",
      "Замбия"
    ],
    "level": 4
  },
  {
    "question": "mw.png",
    "answer": "Малави",
    "isImg": true,
    "answers": [
      "Малави",
      "Замбия",
      "Мозамбик",
      "Зимбабве",
      "Танзания",
      "Лесото"
    ],
    "level": 4
  },
  {
    "question": "ls.png",
    "answer": "Лесото",
    "isImg": true,
    "answers": [
      "Лесото",
      "Эсватини",
      "Ботсвана",
      "ЮАР",
      "Намибия",
      "Ангола"
    ],
    "level": 4
  },
  {
    "question": "kn.png",
    "answer": "Сент-Китс и Невис",
    "isImg": true,
    "answers": [
      "Сент-Китс и Невис",
      "Сент-Люсия",
      "Барбадос",
      "Гренада",
      "Доминика",
      "Антигуа и Барбуда"
    ],
    "level": 4
  },
  {
    "question": "ag.png",
    "answer": "Антигуа и Барбуда",
    "isImg": true,
    "answers": [
      "Антигуа и Барбуда",
      "Сент-Китс и Невис",
      "Барбадос",
      "Доминика",
      "Гренада",
      "Сент-Винсент и Гренадины"
    ],
    "level": 4
  },
  {
    "question": "sc.png",
    "answer": "Сейшельские острова",
    "isImg": true,
    "answers": [
      "Сейшельские острова",
      "Маврикий",
      "Коморские острова",
      "Мальдивы",
      "Мадагаскар",
      "Шри-Ланка"
    ],
    "level": 4
  },
  {
    "question": "fm.png",
    "answer": "Микронезия",
    "isImg": true,
    "answers": [
      "Микронезия",
      "Палау",
      "Маршалловы Острова",
      "Кирибати",
      "Тувалу",
      "Науру"
    ],
    "level": 4
  },
  {
    "question": "nr.png",
    "answer": "Науру",
    "isImg": true,
    "answers": [
      "Науру",
      "Кирибати",
      "Тувалу",
      "Микронезия",
      "Маршалловы Острова",
      "Палау"
    ],
    "level": 4
  },
  {
    "question": "mh.png",
    "answer": "Маршалловы Острова",
    "isImg": true,
    "answers": [
      "Маршалловы Острова",
      "Микронезия",
      "Палау",
      "Кирибати",
      "Тувалу",
      "Науру"
    ],
    "level": 4
  },
  {
    "question": "sb.png",
    "answer": "Соломоновы Острова",
    "isImg": true,
    "answers": [
      "Соломоновы Острова",
      "Вануату",
      "Папуа-Новая Гвинея",
      "Фиджи",
      "Самоа",
      "Тонга"
    ],
    "level": 4
  },
  {
    "question": "vu.png",
    "answer": "Вануату",
    "isImg": true,
    "answers": [
      "Вануату",
      "Соломоновы Острова",
      "Фиджи",
      "Самоа",
      "Тонга",
      "Кирибати"
    ],
    "level": 4
  },
  {
    "question": "to.png",
    "answer": "Тонга",
    "isImg": true,
    "answers": [
      "Тонга",
      "Самоа",
      "Фиджи",
      "Вануату",
      "Соломоновы Острова",
      "Тувалу"
    ],
    "level": 4
  },
  {
    "question": "ws.png",
    "answer": "Самоа",
    "isImg": true,
    "answers": [
      "Самоа",
      "Тонга",
      "Фиджи",
      "Вануату",
      "Соломоновы Острова",
      "Тувалу"
    ],
    "level": 4
  },
  {
    "question": "ki.png",
    "answer": "Кирибати",
    "isImg": true,
    "answers": [
      "Кирибати",
      "Тувалу",
      "Науру",
      "Маршалловы Острова",
      "Микронезия",
      "Палау"
    ],
    "level": 4
  },
  {
    "question": "tv.png",
    "answer": "Тувалу",
    "isImg": true,
    "answers": [
      "Тувалу",
      "Кирибати",
      "Науру",
      "Маршалловы Острова",
      "Микронезия",
      "Палау"
    ],
    "level": 4
  },
  {
    "question": "am.png",
    "answer": "Армения",
    "answers": [
      "Армения",
      "Грузия",
      "Азербайджан",
      "Турция",
      "Иран",
      "Ирак"
    ],
    "level": 3,
    "isImg": true
  },
  {
    "question": "az.png",
    "answer": "Азербайджан",
    "answers": [
      "Азербайджан",
      "Армения",
      "Грузия",
      "Казахстан",
      "Турция",
      "Россия"
    ],
    "level": 3,
    "isImg": true
  },
  {
    "question": "by.png",
    "answer": "Беларусь",
    "answers": [
      "Беларусь",
      "Россия",
      "Украина",
      "Польша",
      "Литва",
      "Латвия"
    ],
    "level": 3,
    "isImg": true
  },
  {
    "question": "md.png",
    "answer": "Молдова",
    "answers": [
      "Молдова",
      "Румыния",
      "Украина",
      "Болгария",
      "Венгрия",
      "Польша"
    ],
    "level": 3,
    "isImg": true
  },
  {
    "question": "me.png",
    "answer": "Черногория",
    "answers": [
      "Черногория",
      "Сербия",
      "Босния и Герцеговина",
      "Албания",
      "Хорватия",
      "Северная Македония"
    ],
    "level": 3,
    "isImg": true
  },
  {
    "question": "na.png",
    "answer": "Намибия",
    "answers": [
      "Намибия",
      "Ботсвана",
      "ЮАР",
      "Ангола",
      "Замбия",
      "Зимбабве"
    ],
    "level": 3,
    "isImg": true
  },
  {
    "question": "py.png",
    "answer": "Парагвай",
    "answers": [
      "Парагвай",
      "Уругвай",
      "Аргентина",
      "Бразилия",
      "Боливия",
      "Перу"
    ],
    "level": 3,
    "isImg": true
  },
  {
    "question": "tm.png",
    "answer": "Туркменистан",
    "answers": [
      "Туркменистан",
      "Узбекистан",
      "Казахстан",
      "Иран",
      "Афганистан",
      "Таджикистан"
    ],
    "level": 3,
    "isImg": true
  },
  {
    "question": "uz.png",
    "answer": "Узбекистан",
    "answers": [
      "Узбекистан",
      "Казахстан",
      "Туркменистан",
      "Таджикистан",
      "Кыргызстан",
      "Афганистан"
    ],
    "level": 3,
    "isImg": true
  },
  {
    "question": "kg.png",
    "answer": "Кыргызстан",
    "answers": [
      "Кыргызстан",
      "Узбекистан",
      "Казахстан",
      "Таджикистан",
      "Афганистан",
      "Туркменистан"
    ],
    "level": 3,
    "isImg": true
  },
  {
    "question": "bo.png",
    "answer": "Боливия",
    "answers": [
      "Боливия",
      "Перу",
      "Парагвай",
      "Аргентина",
      "Бразилия",
      "Чили"
    ],
    "level": 3,
    "isImg": true
  },
  {
    "question": "tg.png",
    "answer": "Того",
    "answers": [
      "Того",
      "Бенин",
      "Гана",
      "Буркина-Фасо",
      "Кот-д'Ивуар",
      "Нигерия"
    ],
    "level": 3,
    "isImg": true
  },
  {
    "question": "zw.png",
    "answer": "Зимбабве",
    "answers": [
      "Зимбабве",
      "Замбия",
      "Ботсвана",
      "Мозамбик",
      "Намибия",
      "ЮАР"
    ],
    "level": 3,
    "isImg": true
  },
  {
    "question": "gm.png",
    "answer": "Гамбия",
    "answers": [
      "Гамбия",
      "Сенегал",
      "Гвинея-Бисау",
      "Гвинея",
      "Сьерра-Леоне",
      "Мавритания"
    ],
    "level": 3,
    "isImg": true
  },
  {
    "question": "bw.png",
    "answer": "Ботсвана",
    "answers": [
      "Ботсвана",
      "Зимбабве",
      "Намибия",
      "ЮАР",
      "Ангола",
      "Замбия"
    ],
    "level": 3,
    "isImg": true
  },
  {
    "question": "cf.png",
    "answer": "Центральноафриканская Республика",
    "answers": [
      "Центральноафриканская Республика",
      "Чад",
      "Судан",
      "Камерун",
      "Демократическая Республика Конго",
      "Южный Судан"
    ],
    "level": 3,
    "isImg": true
  },
  {
    "question": "lr.png",
    "answer": "Либерия",
    "answers": [
      "Либерия",
      "Сьерра-Леоне",
      "Гвинея",
      "Кот-д'Ивуар",
      "Гана",
      "Нигерия"
    ],
    "level": 3,
    "isImg": true
  },
  {
    "question": "tm.png",
    "answer": "Туркменистан",
    "answers": [
      "Туркменистан",
      "Узбекистан",
      "Казахстан",
      "Иран",
      "Афганистан",
      "Таджикистан"
    ],
    "level": 3,
    "isImg": true
  },
  {
    "question": "lb.png",
    "answer": "Ливан",
    "answers": [
      "Ливан",
      "Сирия",
      "Израиль",
      "Иордания",
      "Палестина",
      "Кипр"
    ],
    "level": 3,
    "isImg": true
  },
  {
    "question": "tn.png",
    "answer": "Тунис",
    "answers": [
      "Тунис",
      "Марокко",
      "Алжир",
      "Ливия",
      "Египет",
      "Судан"
    ],
    "level": 3,
    "isImg": true
  },
  {
    "question": "Польша",
    "answer": "pl.png",
    "answers": [
      "pl.png",
      "de.png",
      "cz.png",
      "ск.png",
      "lt.png",
      "ua.png"
    ],
    "level": 1,
    "isTile": true
  },
  {
    "question": "Испания",
    "answer": "es.png",
    "answers": [
      "es.png",
      "it.png",
      "pt.png",
      "fr.png",
      "gr.png",
      "mt.png"
    ],
    "level": 1,
    "isTile": true
  },
  {
    "question": "Аргентина",
    "answer": "ar.png",
    "answers": [
      "ar.png",
      "cl.png",
      "uy.png",
      "br.png",
      "py.png",
      "bo.png"
    ],
    "level": 1,
    "isTile": true
  },
  {
    "question": "Китай",
    "answer": "cn.png",
    "answers": [
      "cn.png",
      "jp.png",
      "kr.png",
      "vn.png",
      "tw.png",
      "in.png"
    ],
    "level": 1,
    "isTile": true
  },
  {
    "question": "Индия",
    "answer": "in.png",
    "answers": [
      "in.png",
      "pk.png",
      "bd.png",
      "lk.png",
      "np.png",
      "mm.png"
    ],
    "level": 1,
    "isTile": true
  },
  {
    "question": "Австралия",
    "answer": "au.png",
    "answers": [
      "au.png",
      "nz.png",
      "fj.png",
      "pg.png",
      "sb.png",
      "id.png"
    ],
    "level": 1,
    "isTile": true
  },
  {
    "question": "Канада",
    "answer": "ca.png",
    "answers": [
      "ca.png",
      "us.png",
      "mx.png",
      "gt.png",
      "bz.png",
      "hn.png"
    ],
    "level": 1,
    "isTile": true
  },
  {
    "question": "ЮАР",
    "answer": "za.png",
    "answers": [
      "za.png",
      "na.png",
      "bw.png",
      "zm.png",
      "mz.png",
      "sz.png"
    ],
    "level": 2,
    "isTile": true
  },
  {
    "question": "Эфиопия",
    "answer": "et.png",
    "answers": [
      "et.png",
      "so.png",
      "dj.png",
      "sd.png",
      "э.png",
      "ke.png"
    ],
    "level": 2,
    "isTile": true
  },
  {
    "question": "Ирак",
    "answer": "iq.png",
    "answers": [
      "iq.png",
      "sy.png",
      "jo.png",
      "sa.png",
      "ir.png",
      "tr.png"
    ],
    "level": 2,
    "isTile": true
  },
  {
    "question": "Вьетнам",
    "answer": "vn.png",
    "answers": [
      "vn.png",
      "th.png",
      "kh.png",
      "la.png",
      "mm.png",
      "my.png"
    ],
    "level": 2,
    "isTile": true
  },
  {
    "question": "Норвегия",
    "answer": "no.png",
    "answers": [
      "no.png",
      "se.png",
      "dk.png",
      "fi.png",
      "is.png",
      "gb.png"
    ],
    "level": 2,
    "isTile": true
  },
  {
    "question": "Марокко",
    "answer": "ma.png",
    "answers": [
      "ma.png",
      "dz.png",
      "tn.png",
      "ly.png",
      "мистер.png",
      "pt.png"
    ],
    "level": 2,
    "isTile": true
  },
  {
    "question": "Кения",
    "answer": "ke.png",
    "answers": [
      "ke.png",
      "tz.png",
      "ug.png",
      "so.png",
      "et.png",
      "cc.png"
    ],
    "level": 2,
    "isTile": true
  },
  {
    "question": "Сербия",
    "answer": "rs.png",
    "answers": [
      "rs.png",
      "hr.png",
      "я.png",
      "ba.png",
      "mk.png",
      "bg.png"
    ],
    "level": 2,
    "isTile": true
  },
  {
    "question": "Чили",
    "answer": "cl.png",
    "answers": [
      "cl.png",
      "ar.png",
      "bo.png",
      "py.png",
      "pe.png",
      "uy.png"
    ],
    "level": 2,
    "isTile": true
  },
  {
    "question": "Узбекистан",
    "answer": "uz.png",
    "answers": [
      "uz.png",
      "tm.png",
      "kg.png",
      "tj.png",
      "kz.png",
      "af.png"
    ],
    "level": 3,
    "isTile": true
  },
  {
    "question": "Казахстан",
    "answer": "kz.png",
    "answers": [
      "kz.png",
      "uz.png",
      "kg.png",
      "tm.png",
      "ru.png",
      "cn.png"
    ],
    "level": 3,
    "isTile": true
  },
  {
    "question": "Иордания",
    "answer": "jo.png",
    "answers": [
      "jo.png",
      "il.png",
      "ps.png",
      "sa.png",
      "sy.png",
      "lb.png"
    ],
    "level": 3,
    "isTile": true
  },
  {
    "question": "Катар",
    "answer": "qa.png",
    "answers": [
      "qa.png",
      "ae.png",
      "bh.png",
      "кв.png",
      "sa.png",
      "om.png"
    ],
    "level": 3,
    "isTile": true
  },
  {
    "question": "Албания",
    "answer": "ал.png",
    "answers": [
      "ал.png",
      "я.png",
      "rs.png",
      "gr.png",
      "mk.png",
      "hr.png"
    ],
    "level": 3,
    "isTile": true
  },
  {
    "question": "Танзания",
    "answer": "tz.png",
    "answers": [
      "tz.png",
      "ke.png",
      "ug.png",
      "rw.png",
      "bi.png",
      "zm.png"
    ],
    "level": 3,
    "isTile": true
  },
  {
    "question": "Мавритания",
    "answer": "мистер.png",
    "answers": [
      "мистер.png",
      "мл.png",
      "dz.png",
      "ma.png",
      "sn.png",
      "gn.png"
    ],
    "level": 3,
    "isTile": true
  },
  {
    "question": "Гондурас",
    "answer": "hn.png",
    "answers": [
      "hn.png",
      "gt.png",
      "св.png",
      "ни.png",
      "cr.png",
      "mx.png"
    ],
    "level": 3,
    "isTile": true
  },
  {
    "question": "Кыргызстан",
    "answer": "kg.png",
    "answers": [
      "kg.png",
      "kz.png",
      "uz.png",
      "tj.png",
      "cn.png",
      "tm.png"
    ],
    "level": 3,
    "isTile": true
  },
  {
    "question": "Мадагаскар",
    "answer": "mg.png",
    "answers": [
      "mg.png",
      "mu.png",
      "sc.png",
      "zm.png",
      "zm.png",
      "za.png"
    ],
    "level": 3,
    "isTile": true
  },
  {
    "question": "Габон",
    "answer": "ga.png",
    "answers": [
      "ga.png",
      "cg.png",
      "см.png",
      "gq.png",
      "ao.png",
      "td.png"
    ],
    "level": 3,
    "isTile": true
  },
  {
    "question": "Багамы",
    "answer": "bs.png",
    "answers": [
      "bs.png",
      "bb.png",
      "jm.png",
      "ht.png",
      "tc.png",
      "cu.png"
    ],
    "level": 3,
    "isTile": true
  },
  {
    "question": "Гана",
    "answer": "gh.png",
    "answers": [
      "gh.png",
      "ci.png",
      "tg.png",
      "bf.png",
      "ng.png",
      "sn.png"
    ],
    "level": 3,
    "isTile": true
  },
  {
    "question": "Папуа-Новая Гвинея",
    "answer": "pg.png",
    "answers": [
      "pg.png",
      "sb.png",
      "vu.png",
      "fj.png",
      "nz.png",
      "au.png"
    ],
    "level": 3,
    "isTile": true
  },
  {
    "question": "Замбия",
    "answer": "zm.png",
    "answers": [
      "zm.png",
      "zw.png",
      "mw.png",
      "ao.png",
      "компакт-диск.png",
      "mz.png"
    ],
    "level": 3,
    "isTile": true
  },
  {
    "question": "Шри-Ланка",
    "answer": "lk.png",
    "answers": [
      "lk.png",
      "in.png",
      "mv.png",
      "bn.png",
      "mm.png",
      "pk.png"
    ],
    "level": 4,
    "isTile": true
  },
  {
    "question": "Сейшельские острова",
    "answer": "sc.png",
    "answers": [
      "sc.png",
      "mu.png",
      "mg.png",
      "mv.png",
      "za.png",
      "ke.png"
    ],
    "level": 4,
    "isTile": true
  },
  {
    "question": "Нигер",
    "answer": "ne.png",
    "answers": [
      "ne.png",
      "мл.png",
      "td.png",
      "ng.png",
      "dz.png",
      "ly.png"
    ],
    "level": 4,
    "isTile": true
  },
  {
    "question": "Джибути",
    "answer": "dj.png",
    "answers": [
      "dj.png",
      "et.png",
      "so.png",
      "э.png",
      "sd.png",
      "ye.png"
    ],
    "level": 4,
    "isTile": true
  },
  {
    "question": "Лесото",
    "answer": "ls.png",
    "answers": [
      "ls.png",
      "sz.png",
      "za.png",
      "mz.png",
      "na.png",
      "bw.png"
    ],
    "level": 4,
    "isTile": true
  },
  {
    "question": "Бурунди",
    "answer": "bi.png",
    "answers": [
      "bi.png",
      "rw.png",
      "ug.png",
      "tz.png",
      "компакт-диск.png",
      "ke.png"
    ],
    "level": 4,
    "isTile": true
  },
  {
    "question": "Гвинея-Бисау",
    "answer": "gw.png",
    "answers": [
      "gw.png",
      "gn.png",
      "sn.png",
      "lr.png",
      "сл.png",
      "ci.png"
    ],
    "level": 4,
    "isTile": true
  },
  {
    "question": "Эсватини",
    "answer": "sz.png",
    "answers": [
      "sz.png",
      "ls.png",
      "za.png",
      "mz.png",
      "bw.png",
      "na.png"
    ],
    "level": 4,
    "isTile": true
  },
  {
    "question": "pl.png",
    "answer": "Польша",
    "answers": [
      "Польша",
      "Германия",
      "Чешская Республика",
      "Австрия",
      "Литва",
      "Словакия"
    ],
    "level": 1,
    "isImg": true
  },
  {
    "question": "es.png",
    "answer": "Испания",
    "answers": [
      "Испания",
      "Португалия",
      "Франция",
      "Италия",
      "Греция",
      "Андорра"
    ],
    "level": 1,
    "isImg": true
  },
  {
    "question": "us.png",
    "answer": "Соединенные Штаты",
    "answers": [
      "Соединенные Штаты",
      "Канада",
      "Мексика",
      "Австралия",
      "Великобритания",
      "Новая Зеландия"
    ],
    "level": 1,
    "isImg": true
  },
  {
    "question": "fr.png",
    "answer": "Франция",
    "answers": [
      "Франция",
      "Бельгия",
      "Швейцария",
      "Италия",
      "Люксембург",
      "Испания"
    ],
    "level": 1,
    "isImg": true
  },
  {
    "question": "it.png",
    "answer": "Италия",
    "answers": [
      "Италия",
      "Греция",
      "Франция",
      "Испания",
      "Португалия",
      "Швейцария"
    ],
    "level": 1,
    "isImg": true
  },
  {
    "question": "gb.png",
    "answer": "Великобритания",
    "answers": [
      "Великобритания",
      "Ирландия",
      "Австралия",
      "Канада",
      "Новая Зеландия",
      "Соединенные Штаты"
    ],
    "level": 1,
    "isImg": true
  },
  {
    "question": "de.png",
    "answer": "Германия",
    "answers": [
      "Германия",
      "Нидерланды",
      "Польша",
      "Австрия",
      "Бельгия",
      "Дания"
    ],
    "level": 1,
    "isImg": true
  },
  {
    "question": "ca.png",
    "answer": "Канада",
    "answers": [
      "Канада",
      "Соединенные Штаты",
      "Австралия",
      "Новая Зеландия",
      "Великобритания",
      "Мексика"
    ],
    "level": 1,
    "isImg": true
  },
  {
    "question": "br.png",
    "answer": "Бразилия",
    "answers": [
      "Бразилия",
      "Аргентина",
      "Чили",
      "Уругвай",
      "Парагвай",
      "Колумбия"
    ],
    "level": 1,
    "isImg": true
  },
  {
    "question": "au.png",
    "answer": "Австралия",
    "answers": [
      "Австралия",
      "Новая Зеландия",
      "Великобритания",
      "Канада",
      "ЮАР",
      "Соединенные Штаты"
    ],
    "level": 1,
    "isImg": true
  },
  {
    "question": "mx.png",
    "answer": "Мексика",
    "answers": [
      "Мексика",
      "Гватемала",
      "Соединенные Штаты",
      "Бразилия",
      "Куба",
      "Колумбия"
    ],
    "level": 1,
    "isImg": true
  },
  {
    "question": "ar.png",
    "answer": "Аргентина",
    "answers": [
      "Аргентина",
      "Бразилия",
      "Чили",
      "Уругвай",
      "Парагвай",
      "Боливия"
    ],
    "level": 1,
    "isImg": true
  },
  {
    "question": "jp.png",
    "answer": "Япония",
    "answers": [
      "Япония",
      "Китай",
      "Южная Корея",
      "Филиппины",
      "Вьетнам",
      "Тайвань"
    ],
    "level": 1,
    "isImg": true
  },
  {
    "question": "kr.png",
    "answer": "Южная Корея",
    "answers": [
      "Южная Корея",
      "Япония",
      "Китай",
      "Тайвань",
      "Вьетнам",
      "Филиппины"
    ],
    "level": 1,
    "isImg": true
  },
  {
    "question": "cn.png",
    "answer": "Китай",
    "answers": [
      "Китай",
      "Япония",
      "Южная Корея",
      "Вьетнам",
      "Тайвань",
      "Монголия"
    ],
    "level": 1,
    "isImg": true
  },
  {
    "question": "ru.png",
    "answer": "Россия",
    "answers": [
      "Россия",
      "Украина",
      "Казахстан",
      "Беларусь",
      "Монголия",
      "Китай"
    ],
    "level": 1,
    "isImg": true
  },
  {
    "question": "in.png",
    "answer": "Индия",
    "answers": [
      "Индия",
      "Пакистан",
      "Бангладеш",
      "Шри-Ланка",
      "Непал",
      "Мьянма"
    ],
    "level": 1,
    "isImg": true
  },
  {
    "question": "za.png",
    "answer": "ЮАР",
    "answers": [
      "ЮАР",
      "Намибия",
      "Ботсвана",
      "Зимбабве",
      "Мозамбик",
      "Ангола"
    ],
    "level": 1,
    "isImg": true
  },
  {
    "question": "eg.png",
    "answer": "Египет",
    "answers": [
      "Египет",
      "Судан",
      "Ливия",
      "Тунис",
      "Иордания",
      "Алжир"
    ],
    "level": 1,
    "isImg": true
  },
  {
    "question": "sa.png",
    "answer": "Саудовская Аравия",
    "answers": [
      "Саудовская Аравия",
      "Объединенные Арабские Эмираты",
      "Катар",
      "Йемен",
      "Иордания",
      "Оман"
    ],
    "level": 1,
    "isImg": true
  },
  {
    "question": "qa.png",
    "answer": "Катар",
    "answers": [
      "Катар",
      "Бахрейн",
      "Объединенные Арабские Эмираты",
      "Кувейт",
      "Саудовская Аравия",
      "Оман"
    ],
    "level": 2,
    "isImg": true
  },
  {
    "question": "ae.png",
    "answer": "Объединенные Арабские Эмираты",
    "answers": [
      "Объединенные Арабские Эмираты",
      "Катар",
      "Кувейт",
      "Саудовская Аравия",
      "Оман",
      "Бахрейн"
    ],
    "level": 2,
    "isImg": true
  },
  {
    "question": "ch.png",
    "answer": "Швейцария",
    "answers": [
      "Швейцария",
      "Австрия",
      "Германия",
      "Франция",
      "Италия",
      "Бельгия"
    ],
    "level": 2,
    "isImg": true
  },
  {
    "question": "at.png",
    "answer": "Австрия",
    "answers": [
      "Австрия",
      "Германия",
      "Швейцария",
      "Чешская Республика",
      "Словакия",
      "Венгрия"
    ],
    "level": 2,
    "isImg": true
  },
  {
    "question": "dk.png",
    "answer": "Дания",
    "answers": [
      "Дания",
      "Швеция",
      "Норвегия",
      "Германия",
      "Финляндия",
      "Нидерланды"
    ],
    "level": 2,
    "isImg": true
  },
  {
    "question": "se.png",
    "answer": "Швеция",
    "answers": [
      "Швеция",
      "Норвегия",
      "Дания",
      "Финляндия",
      "Исландия",
      "Германия"
    ],
    "level": 2,
    "isImg": true
  },
  {
    "question": "no.png",
    "answer": "Норвегия",
    "answers": [
      "Норвегия",
      "Швеция",
      "Дания",
      "Финляндия",
      "Исландия",
      "Гренландия"
    ],
    "level": 2,
    "isImg": true
  },
  {
    "question": "fi.png",
    "answer": "Финляндия",
    "answers": [
      "Финляндия",
      "Швеция",
      "Норвегия",
      "Россия",
      "Эстония",
      "Дания"
    ],
    "level": 2,
    "isImg": true
  },
  {
    "question": "gr.png",
    "answer": "Греция",
    "answers": [
      "Греция",
      "Кипр",
      "Турция",
      "Болгария",
      "Албания",
      "Италия"
    ],
    "level": 2,
    "isImg": true
  },
  {
    "question": "tr.png",
    "answer": "Турция",
    "answers": [
      "Турция",
      "Греция",
      "Кипр",
      "Болгария",
      "Сирия",
      "Иран"
    ],
    "level": 2,
    "isImg": true
  },
  {
    "question": "pt.png",
    "answer": "Португалия",
    "answers": [
      "Португалия",
      "Испания",
      "Франция",
      "Италия",
      "Бразилия",
      "Аргентина"
    ],
    "level": 2,
    "isImg": true
  },
  {
    "question": "nz.png",
    "answer": "Новая Зеландия",
    "answers": [
      "Новая Зеландия",
      "Австралия",
      "Фиджи",
      "Папуа-Новая Гвинея",
      "Тонга",
      "Самоа"
    ],
    "level": 2,
    "isImg": true
  },
  {
    "question": "my.png",
    "answer": "Малайзия",
    "answers": [
      "Малайзия",
      "Индонезия",
      "Сингапур",
      "Филиппины",
      "Таиланд",
      "Вьетнам"
    ],
    "level": 2,
    "isImg": true
  },
  {
    "question": "sg.png",
    "answer": "Сингапур",
    "answers": [
      "Сингапур",
      "Малайзия",
      "Индонезия",
      "Филиппины",
      "Таиланд",
      "Вьетнам"
    ],
    "level": 2,
    "isImg": true
  },
  {
    "question": "vn.png",
    "answer": "Вьетнам",
    "answers": [
      "Вьетнам",
      "Камбоджа",
      "Лаос",
      "Таиланд",
      "Малайзия",
      "Мьянма"
    ],
    "level": 2,
    "isImg": true
  },
  {
    "question": "th.png",
    "answer": "Таиланд",
    "answers": [
      "Таиланд",
      "Камбоджа",
      "Лаос",
      "Мьянма",
      "Вьетнам",
      "Малайзия"
    ],
    "level": 2,
    "isImg": true
  },
  {
    "question": "ph.png",
    "answer": "Филиппины",
    "answers": [
      "Филиппины",
      "Малайзия",
      "Индонезия",
      "Вьетнам",
      "Таиланд",
      "Тайвань"
    ],
    "level": 2,
    "isImg": true
  },
  {
    "question": "by.png",
    "answer": "Беларусь",
    "answers": [
      "Беларусь",
      "Россия",
      "Украина",
      "Польша",
      "Литва",
      "Латвия"
    ],
    "level": 3,
    "isImg": true
  },
  {
    "question": "ua.png",
    "answer": "Украина",
    "answers": [
      "Украина",
      "Россия",
      "Беларусь",
      "Польша",
      "Румыния",
      "Молдова"
    ],
    "level": 3,
    "isImg": true
  },
  {
    "question": "bg.png",
    "answer": "Болгария",
    "answers": [
      "Болгария",
      "Греция",
      "Турция",
      "Румыния",
      "Сербия",
      "Северная Македония"
    ],
    "level": 3,
    "isImg": true
  },
  {
    "question": "ro.png",
    "answer": "Румыния",
    "answers": [
      "Румыния",
      "Молдова",
      "Болгария",
      "Украина",
      "Сербия",
      "Венгрия"
    ],
    "level": 3,
    "isImg": true
  },
  {
    "question": "hu.png",
    "answer": "Венгрия",
    "answers": [
      "Венгрия",
      "Австрия",
      "Словакия",
      "Румыния",
      "Сербия",
      "Хорватия"
    ],
    "level": 3,
    "isImg": true
  },
  {
    "question": "cz.png",
    "answer": "Чешская Республика",
    "answers": [
      "Чешская Республика",
      "Словакия",
      "Польша",
      "Германия",
      "Австрия",
      "Венгрия"
    ],
    "level": 3,
    "isImg": true
  },
  {
    "question": "ск.png",
    "answer": "Словакия",
    "answers": [
      "Словакия",
      "Чешская Республика",
      "Польша",
      "Венгрия",
      "Австрия",
      "Украина"
    ],
    "level": 3,
    "isImg": true
  },
  {
    "question": "lt.png",
    "answer": "Литва",
    "answers": [
      "Литва",
      "Латвия",
      "Польша",
      "Беларусь",
      "Россия",
      "Эстония"
    ],
    "level": 3,
    "isImg": true
  },
  {
    "question": "lv.png",
    "answer": "Латвия",
    "answers": [
      "Латвия",
      "Литва",
      "Эстония",
      "Россия",
      "Беларусь",
      "Финляндия"
    ],
    "level": 3,
    "isImg": true
  },
  {
    "question": "ee.png",
    "answer": "Эстония",
    "answers": [
      "Эстония",
      "Латвия",
      "Финляндия",
      "Россия",
      "Литва",
      "Швеция"
    ],
    "level": 3,
    "isImg": true
  },
  {
    "question": "ge.png",
    "answer": "Грузия",
    "answers": [
      "Грузия",
      "Армения",
      "Азербайджан",
      "Турция",
      "Россия",
      "Иран"
    ],
    "level": 3,
    "isImg": true
  },
  {
    "question": "am.png",
    "answer": "Армения",
    "answers": [
      "Армения",
      "Грузия",
      "Азербайджан",
      "Турция",
      "Иран",
      "Россия"
    ],
    "level": 3,
    "isImg": true
  },
  {
    "question": "az.png",
    "answer": "Азербайджан",
    "answers": [
      "Азербайджан",
      "Армения",
      "Грузия",
      "Иран",
      "Турция",
      "Россия"
    ],
    "level": 3,
    "isImg": true
  },
  {
    "question": "kg.png",
    "answer": "Кыргызстан",
    "answers": [
      "Кыргызстан",
      "Казахстан",
      "Узбекистан",
      "Таджикистан",
      "Туркменистан",
      "Россия"
    ],
    "level": 3,
    "isImg": true
  },
  {
    "question": "uz.png",
    "answer": "Узбекистан",
    "answers": [
      "Узбекистан",
      "Казахстан",
      "Кыргызстан",
      "Таджикистан",
      "Туркменистан",
      "Афганистан"
    ],
    "level": 3,
    "isImg": true
  },
  {
    "question": "tm.png",
    "answer": "Туркменистан",
    "answers": [
      "Туркменистан",
      "Узбекистан",
      "Казахстан",
      "Афганистан",
      "Иран",
      "Кыргызстан"
    ],
    "level": 3,
    "isImg": true
  },
  {
    "question": "tj.png",
    "answer": "Таджикистан",
    "answers": [
      "Таджикистан",
      "Кыргызстан",
      "Узбекистан",
      "Афганистан",
      "Туркменистан",
      "Китай"
    ],
    "level": 3,
    "isImg": true
  },
  {
    "question": "мн.png",
    "answer": "Монголия",
    "answers": [
      "Монголия",
      "Китай",
      "Россия",
      "Казахстан",
      "Кыргызстан",
      "Япония"
    ],
    "level": 3,
    "isImg": true
  },
  {
    "question": "af.png",
    "answer": "Афганистан",
    "answers": [
      "Афганистан",
      "Пакистан",
      "Иран",
      "Таджикистан",
      "Узбекистан",
      "Туркменистан"
    ],
    "level": 4,
    "isImg": true
  },
  {
    "question": "np.png",
    "answer": "Непал",
    "answers": [
      "Непал",
      "Индия",
      "Китай",
      "Бутан",
      "Бангладеш",
      "Шри-Ланка"
    ],
    "level": 4,
    "isImg": true
  },
  {
    "question": "bt.png",
    "answer": "Бутан",
    "answers": [
      "Бутан",
      "Индия",
      "Китай",
      "Непал",
      "Бангладеш",
      "Мьянма"
    ],
    "level": 4,
    "isImg": true
  },
  {
    "question": "la.png",
    "answer": "Лаос",
    "answers": [
      "Лаос",
      "Вьетнам",
      "Таиланд",
      "Камбоджа",
      "Мьянма",
      "Китай"
    ],
    "level": 4,
    "isImg": true
  },
  {
    "question": "kh.png",
    "answer": "Камбоджа",
    "answers": [
      "Камбоджа",
      "Лаос",
      "Вьетнам",
      "Таиланд",
      "Мьянма",
      "Малайзия"
    ],
    "level": 4,
    "isImg": true
  },
  {
    "question": "mm.png",
    "answer": "Мьянма",
    "answers": [
      "Мьянма",
      "Таиланд",
      "Лаос",
      "Бангладеш",
      "Китай",
      "Индия"
    ],
    "level": 4,
    "isImg": true
  },
  {
    "question": "bd.png",
    "answer": "Бангладеш",
    "answers": [
      "Бангладеш",
      "Индия",
      "Мьянма",
      "Непал",
      "Бутан",
      "Пакистан"
    ],
    "level": 4,
    "isImg": true
  },
  {
    "question": "pk.png",
    "answer": "Пакистан",
    "answers": [
      "Пакистан",
      "Индия",
      "Афганистан",
      "Иран",
      "Китай",
      "Непал"
    ],
    "level": 4,
    "isImg": true
  },
  {
    "question": "lk.png",
    "answer": "Шри-Ланка",
    "answers": [
      "Шри-Ланка",
      "Индия",
      "Мальдивы",
      "Бангладеш",
      "Непал",
      "Бутан"
    ],
    "level": 4,
    "isImg": true
  },
  {
    "question": "ir.png",
    "answer": "Иран",
    "answers": [
      "Иран",
      "Ирак",
      "Афганистан",
      "Пакистан",
      "Турция",
      "Туркменистан"
    ],
    "level": 4,
    "isImg": true
  },
  {
    "question": "iq.png",
    "answer": "Ирак",
    "answers": [
      "Ирак",
      "Иран",
      "Сирия",
      "Иордания",
      "Турция",
      "Саудовская Аравия"
    ],
    "level": 4,
    "isImg": true
  },
  {
    "question": "sy.png",
    "answer": "Сирия",
    "answers": [
      "Сирия",
      "Ирак",
      "Ливан",
      "Иордания",
      "Турция",
      "Израиль"
    ],
    "level": 4,
    "isImg": true
  },
  {
    "question": "jo.png",
    "answer": "Иордания",
    "answers": [
      "Иордания",
      "Сирия",
      "Ирак",
      "Саудовская Аравия",
      "Израиль",
      "Ливан"
    ],
    "level": 4,
    "isImg": true
  },
  {
    "question": "ye.png",
    "answer": "Йемен",
    "answers": [
      "Йемен",
      "Оман",
      "Саудовская Аравия",
      "Катар",
      "Объединенные Арабские Эмираты",
      "Бахрейн"
    ],
    "level": 4,
    "isImg": true
  },
  {
    "question": "om.png",
    "answer": "Оман",
    "answers": [
      "Оман",
      "Йемен",
      "Саудовская Аравия",
      "Катар",
      "Объединенные Арабские Эмираты",
      "Бахрейн"
    ],
    "level": 4,
    "isImg": true
  },
  {
    "question": "Париж – столица",
    "answer": "fr.png",
    "answers": [
      "fr.png",
      "de.png",
      "es.png",
      "it.png",
      "be.png",
      "nl.png"
    ],
    "level": 1,
    "isTile": true
  },
  {
    "question": "Берлин – столица",
    "answer": "de.png",
    "answers": [
      "de.png",
      "fr.png",
      "at.png",
      "be.png",
      "ch.png",
      "it.png"
    ],
    "level": 1,
    "isTile": true
  },
  {
    "question": "Мадрид – столица",
    "answer": "es.png",
    "answers": [
      "es.png",
      "pt.png",
      "fr.png",
      "it.png",
      "gr.png",
      "be.png"
    ],
    "level": 1,
    "isTile": true
  },
  {
    "question": "Рим – столица",
    "answer": "it.png",
    "answers": [
      "it.png",
      "es.png",
      "fr.png",
      "gr.png",
      "at.png",
      "be.png"
    ],
    "level": 1,
    "isTile": true
  },
  {
    "question": "Брюссель – столица",
    "answer": "be.png",
    "answers": [
      "be.png",
      "nl.png",
      "fr.png",
      "de.png",
      "lu.png",
      "it.png"
    ],
    "level": 1,
    "isTile": true
  },
  {
    "question": "Амстердам – столица",
    "answer": "nl.png",
    "answers": [
      "nl.png",
      "be.png",
      "fr.png",
      "de.png",
      "lu.png",
      "dk.png"
    ],
    "level": 1,
    "isTile": true
  },
  {
    "question": "Вена – столица",
    "answer": "at.png",
    "answers": [
      "at.png",
      "de.png",
      "ch.png",
      "it.png",
      "cz.png",
      "ск.png"
    ],
    "level": 1,
    "isTile": true
  },
  {
    "question": "Лиссабон – столица",
    "answer": "pt.png",
    "answers": [
      "pt.png",
      "es.png",
      "fr.png",
      "it.png",
      "de.png",
      "be.png"
    ],
    "level": 1,
    "isTile": true
  },
  {
    "question": "Афины – столица",
    "answer": "gr.png",
    "answers": [
      "gr.png",
      "it.png",
      "fr.png",
      "es.png",
      "pt.png",
      "tr.png"
    ],
    "level": 1,
    "isTile": true
  },
  {
    "question": "Варшава – столица",
    "answer": "pl.png",
    "answers": [
      "pl.png",
      "cz.png",
      "ск.png",
      "hu.png",
      "de.png",
      "lt.png"
    ],
    "level": 1,
    "isTile": true
  },
  {
    "question": "Хельсинки – столица",
    "answer": "fi.png",
    "answers": [
      "fi.png",
      "se.png",
      "no.png",
      "dk.png",
      "ee.png",
      "lt.png"
    ],
    "level": 2,
    "isTile": true
  },
  {
    "question": "Стокгольм – столица",
    "answer": "se.png",
    "answers": [
      "se.png",
      "no.png",
      "fi.png",
      "dk.png",
      "ee.png",
      "lt.png"
    ],
    "level": 2,
    "isTile": true
  },
  {
    "question": "Осло – столица",
    "answer": "no.png",
    "answers": [
      "no.png",
      "se.png",
      "fi.png",
      "dk.png",
      "is.png",
      "ee.png"
    ],
    "level": 2,
    "isTile": true
  },
  {
    "question": "Копенгаген – столица",
    "answer": "dk.png",
    "answers": [
      "dk.png",
      "se.png",
      "no.png",
      "fi.png",
      "is.png",
      "de.png"
    ],
    "level": 2,
    "isTile": true
  },
  {
    "question": "Будапешт – столица",
    "answer": "hu.png",
    "answers": [
      "hu.png",
      "at.png",
      "cz.png",
      "ск.png",
      "pl.png",
      "ro.png"
    ],
    "level": 2,
    "isTile": true
  },
  {
    "question": "Прага – столица",
    "answer": "cz.png",
    "answers": [
      "cz.png",
      "ск.png",
      "pl.png",
      "hu.png",
      "at.png",
      "de.png"
    ],
    "level": 2,
    "isTile": true
  },
  {
    "question": "Бухарест – столица",
    "answer": "ro.png",
    "answers": [
      "ro.png",
      "bg.png",
      "hu.png",
      "rs.png",
      "ua.png",
      "md.png"
    ],
    "level": 2,
    "isTile": true
  },
  {
    "question": "Белград – столица",
    "answer": "rs.png",
    "answers": [
      "rs.png",
      "hr.png",
      "hu.png",
      "ro.png",
      "bg.png",
      "ba.png"
    ],
    "level": 2,
    "isTile": true
  },
  {
    "question": "София – столица",
    "answer": "bg.png",
    "answers": [
      "bg.png",
      "ro.png",
      "gr.png",
      "tr.png",
      "rs.png",
      "mk.png"
    ],
    "level": 2,
    "isTile": true
  },
  {
    "question": "Братислава – столица",
    "answer": "ск.png",
    "answers": [
      "ск.png",
      "cz.png",
      "hu.png",
      "pl.png",
      "at.png",
      "ua.png"
    ],
    "level": 2,
    "isTile": true
  },
  {
    "question": "Ханой – столица",
    "answer": "vn.png",
    "answers": [
      "vn.png",
      "kh.png",
      "la.png",
      "th.png",
      "mm.png",
      "cn.png"
    ],
    "level": 3,
    "isTile": true
  },
  {
    "question": "Бангкок – столица",
    "answer": "th.png",
    "answers": [
      "th.png",
      "kh.png",
      "la.png",
      "vn.png",
      "mm.png",
      "my.png"
    ],
    "level": 3,
    "isTile": true
  },
  {
    "question": "Джакарта – столица",
    "answer": "id.png",
    "answers": [
      "id.png",
      "my.png",
      "th.png",
      "vn.png",
      "sg.png",
      "ph.png"
    ],
    "level": 3,
    "isTile": true
  },
  {
    "question": "Куала-Лумпур – столица",
    "answer": "my.png",
    "answers": [
      "my.png",
      "sg.png",
      "id.png",
      "th.png",
      "vn.png",
      "ph.png"
    ],
    "level": 3,
    "isTile": true
  },
  {
    "question": "Манила – столица",
    "answer": "ph.png",
    "answers": [
      "ph.png",
      "id.png",
      "my.png",
      "th.png",
      "sg.png",
      "vn.png"
    ],
    "level": 3,
    "isTile": true
  },
  {
    "question": "Тегеран – столица",
    "answer": "ir.png",
    "answers": [
      "ir.png",
      "af.png",
      "pk.png",
      "iq.png",
      "tr.png",
      "sy.png"
    ],
    "level": 3,
    "isTile": true
  },
  {
    "question": "Багдад – столица",
    "answer": "iq.png",
    "answers": [
      "iq.png",
      "sy.png",
      "ir.png",
      "tr.png",
      "sa.png",
      "jo.png"
    ],
    "level": 3,
    "isTile": true
  },
  {
    "question": "Дамаск – столица",
    "answer": "sy.png",
    "answers": [
      "sy.png",
      "iq.png",
      "jo.png",
      "ir.png",
      "tr.png",
      "lb.png"
    ],
    "level": 3,
    "isTile": true
  },
  {
    "question": "Амман – столица",
    "answer": "jo.png",
    "answers": [
      "jo.png",
      "sy.png",
      "iq.png",
      "sa.png",
      "lb.png",
      "eg.png"
    ],
    "level": 3,
    "isTile": true
  },
  {
    "question": "Катманду – столица",
    "answer": "np.png",
    "answers": [
      "np.png",
      "in.png",
      "cn.png",
      "bt.png",
      "pk.png",
      "mm.png"
    ],
    "level": 3,
    "isTile": true
  },
  {
    "question": "Ереван – столица",
    "answer": "am.png",
    "answers": [
      "am.png",
      "ge.png",
      "az.png",
      "tr.png",
      "ir.png",
      "ru.png"
    ],
    "level": 4,
    "isTile": true
  },
  {
    "question": "Тбилиси – столица",
    "answer": "ge.png",
    "answers": [
      "ge.png",
      "am.png",
      "az.png",
      "tr.png",
      "ru.png",
      "ir.png"
    ],
    "level": 4,
    "isTile": true
  },
  {
    "question": "Баку – столица",
    "answer": "az.png",
    "answers": [
      "az.png",
      "ge.png",
      "am.png",
      "ru.png",
      "ir.png",
      "tm.png"
    ],
    "level": 4,
    "isTile": true
  },
  {
    "question": "Ашхабад – столица",
    "answer": "tm.png",
    "answers": [
      "tm.png",
      "uz.png",
      "af.png",
      "az.png",
      "ir.png",
      "kg.png"
    ],
    "level": 4,
    "isTile": true
  },
  {
    "question": "Ташкент – столица",
    "answer": "uz.png",
    "answers": [
      "uz.png",
      "tm.png",
      "kg.png",
      "tj.png",
      "af.png",
      "kz.png"
    ],
    "level": 4,
    "isTile": true
  },
  {
    "question": "Бишкек – столица",
    "answer": "kg.png",
    "answers": [
      "kg.png",
      "uz.png",
      "tj.png",
      "kz.png",
      "tm.png",
      "af.png"
    ],
    "level": 4,
    "isTile": true
  },
  {
    "question": "Душанбе – столица",
    "answer": "tj.png",
    "answers": [
      "tj.png",
      "kg.png",
      "uz.png",
      "af.png",
      "tm.png",
      "kz.png"
    ],
    "level": 4,
    "isTile": true
  },
  {
    "question": "Нейпьидо – столица",
    "answer": "mm.png",
    "answers": [
      "mm.png",
      "la.png",
      "th.png",
      "bd.png",
      "np.png",
      "cn.png"
    ],
    "level": 4,
    "isTile": true
  },
  {
    "question": "Исламабад – столица",
    "answer": "pk.png",
    "answers": [
      "pk.png",
      "af.png",
      "in.png",
      "bd.png",
      "np.png",
      "ir.png"
    ],
    "level": 4,
    "isTile": true
  },
  {
    "question": "Эйфелева башня",
    "answer": "Франция",
    "answers": [
      "Франция",
      "Италия",
      "Германия",
      "Испания",
      "Великобритания",
      "Бельгия"
    ],
    "level": 1
  },
  {
    "question": "Статуя Свободы",
    "answer": "Соединенные Штаты",
    "answers": [
      "Соединенные Штаты",
      "Канада",
      "Великобритания",
      "Австралия",
      "Мексика",
      "Бразилия"
    ],
    "level": 1
  },
  {
    "question": "Сиднейский оперный театр",
    "answer": "Австралия",
    "answers": [
      "Австралия",
      "Новая Зеландия",
      "Соединенные Штаты",
      "Великобритания",
      "Канада",
      "ЮАР"
    ],
    "level": 1
  },
  {
    "question": "Великая стена",
    "answer": "Китай",
    "answers": [
      "Китай",
      "Япония",
      "Монголия",
      "Индия",
      "Южная Корея",
      "Вьетнам"
    ],
    "level": 1
  },
  {
    "question": "Христос Искупитель",
    "answer": "Бразилия",
    "answers": [
      "Бразилия",
      "Аргентина",
      "Чили",
      "Колумбия",
      "Венесуэла",
      "Уругвай"
    ],
    "level": 1
  },
  {
    "question": "Мачу-Пикчу",
    "answer": "Перу",
    "answers": [
      "Перу",
      "Чили",
      "Эквадор",
      "Колумбия",
      "Боливия",
      "Бразилия"
    ],
    "level": 1
  },
  {
    "question": "Тадж-Махал",
    "answer": "Индия",
    "answers": [
      "Индия",
      "Пакистан",
      "Бангладеш",
      "Непал",
      "Шри-Ланка",
      "Афганистан"
    ],
    "level": 1
  },
  {
    "question": "Колизей",
    "answer": "Италия",
    "answers": [
      "Италия",
      "Франция",
      "Испания",
      "Греция",
      "Португалия",
      "Турция"
    ],
    "level": 1
  },
  {
    "question": "Гора Фудзи",
    "answer": "Япония",
    "answers": [
      "Япония",
      "Китай",
      "Южная Корея",
      "Филиппины",
      "Таиланд",
      "Вьетнам"
    ],
    "level": 1
  },
  {
    "question": "Биг Бен",
    "answer": "Великобритания",
    "answers": [
      "Великобритания",
      "Соединенные Штаты",
      "Франция",
      "Ирландия",
      "Германия",
      "Нидерланды"
    ],
    "level": 1
  },
  {
    "question": "Озеро Байкал",
    "answer": "Россия",
    "answers": [
      "Россия",
      "Казахстан",
      "Монголия",
      "Китай",
      "Украина",
      "Беларусь"
    ],
    "level": 2
  },
  {
    "question": "Гора Килиманджаро",
    "answer": "Танзания",
    "answers": [
      "Танзания",
      "Кения",
      "Уганда",
      "Эфиопия",
      "ЮАР",
      "Мозамбик"
    ],
    "level": 2
  },
  {
    "question": "Пирамиды Гизы",
    "answer": "Египет",
    "answers": [
      "Египет",
      "Ливия",
      "Судан",
      "Марокко",
      "Саудовская Аравия",
      "Израиль"
    ],
    "level": 2
  },
  {
    "question": "Озеро Титикака",
    "answer": "Боливия",
    "answers": [
      "Боливия",
      "Перу",
      "Эквадор",
      "Чили",
      "Аргентина",
      "Колумбия"
    ],
    "level": 2
  },
  {
    "question": "Петра",
    "answer": "Иордания",
    "answers": [
      "Иордания",
      "Сирия",
      "Израиль",
      "Ливан",
      "Саудовская Аравия",
      "Египет"
    ],
    "level": 2
  },
  {
    "question": "Водопад Виктория",
    "answer": "Зимбабве",
    "answers": [
      "Зимбабве",
      "Замбия",
      "ЮАР",
      "Ботсвана",
      "Намибия",
      "Мозамбик"
    ],
    "level": 2
  },
  {
    "question": "Гора Эверест",
    "answer": "Непал",
    "answers": [
      "Непал",
      "Индия",
      "Бутан",
      "Китай",
      "Пакистан",
      "Бангладеш"
    ],
    "level": 2
  },
  {
    "question": "Ангкор-Ват",
    "answer": "Камбоджа",
    "answers": [
      "Камбоджа",
      "Таиланд",
      "Вьетнам",
      "Лаос",
      "Мьянма",
      "Малайзия"
    ],
    "level": 2
  },
  {
    "question": "Ниагарский водопад",
    "answer": "Канада",
    "answers": [
      "Канада",
      "Соединенные Штаты",
      "Мексика",
      "Куба",
      "Великобритания",
      "Австралия"
    ],
    "level": 2
  },
  {
    "question": "Маттерхорн",
    "answer": "Швейцария",
    "answers": [
      "Швейцария",
      "Италия",
      "Франция",
      "Германия",
      "Австрия",
      "Лихтенштейн"
    ],
    "level": 2
  },
  {
    "question": "Рейкьявик – расположен в",
    "answer": "Исландия",
    "answers": [
      "Исландия",
      "Гренландия",
      "Норвегия",
      "Дания",
      "Финляндия",
      "Швеция"
    ],
    "level": 3
  },
  {
    "question": "Парфенон",
    "answer": "Греция",
    "answers": [
      "Греция",
      "Италия",
      "Турция",
      "Кипр",
      "Испания",
      "Франция"
    ],
    "level": 3
  },
  {
    "question": "Галапагосские острова",
    "answer": "Эквадор",
    "answers": [
      "Эквадор",
      "Перу",
      "Колумбия",
      "Чили",
      "Венесуэла",
      "Бразилия"
    ],
    "level": 3
  },
  {
    "question": "Улуру (Айерс-Рок)",
    "answer": "Австралия",
    "answers": [
      "Австралия",
      "Новая Зеландия",
      "Индонезия",
      "Папуа-Новая Гвинея",
      "Фиджи",
      "Филиппины"
    ],
    "level": 3
  },
  {
    "question": "Мертвое море",
    "answer": "Иордания",
    "answers": [
      "Иордания",
      "Израиль",
      "Саудовская Аравия",
      "Египет",
      "Сирия",
      "Ливан"
    ],
    "level": 3
  },
  {
    "question": "Столовая гора",
    "answer": "ЮАР",
    "answers": [
      "ЮАР",
      "Намибия",
      "Ботсвана",
      "Зимбабве",
      "Лесото",
      "Свазиленд"
    ],
    "level": 3
  },
  {
    "question": "Касабланка",
    "answer": "Марокко",
    "answers": [
      "Марокко",
      "Алжир",
      "Тунис",
      "Египет",
      "Испания",
      "Португалия"
    ],
    "level": 3
  },
  {
    "question": "Озеро Виктория",
    "answer": "Уганда",
    "answers": [
      "Уганда",
      "Кения",
      "Танзания",
      "Руанда",
      "Бурунди",
      "Южный Судан"
    ],
    "level": 3
  },
  {
    "question": "Озеро Малави",
    "answer": "Малави",
    "answers": [
      "Малави",
      "Мозамбик",
      "Танзания",
      "Зимбабве",
      "Замбия",
      "Ботсвана"
    ],
    "level": 4
  },
  {
    "question": "Салар де Уюни",
    "answer": "Боливия",
    "answers": [
      "Боливия",
      "Чили",
      "Перу",
      "Эквадор",
      "Аргентина",
      "Парагвай"
    ],
    "level": 4
  },
  {
    "question": "Тимбукту",
    "answer": "Мали",
    "answers": [
      "Мали",
      "Мавритания",
      "Нигер",
      "Чад",
      "Алжир",
      "Марокко"
    ],
    "level": 4
  },
  {
    "question": "Мавзолей Галикарнаса",
    "answer": "Турция",
    "answers": [
      "Турция",
      "Греция",
      "Египет",
      "Кипр",
      "Италия",
      "Иордания"
    ],
    "level": 4
  },
  {
    "question": "гора Эльбрус",
    "answer": "Россия",
    "answers": [
      "Россия",
      "Грузия",
      "Азербайджан",
      "Турция",
      "Казахстан",
      "Армения"
    ],
    "level": 4
  },
  {
    "question": "Озеро Танганьика",
    "answer": "Танзания",
    "answers": [
      "Танзания",
      "Бурунди",
      "Конго",
      "Замбия",
      "Руанда",
      "Уганда"
    ],
    "level": 4
  },
  {
    "question": "Тропический лес Амазонки",
    "answer": "Бразилия",
    "answers": [
      "Бразилия",
      "Перу",
      "Колумбия",
      "Венесуэла",
      "Боливия",
      "Гайана"
    ],
    "level": 4
  },
  {
    "question": "Луксорский храм",
    "answer": "Египет",
    "answers": [
      "Египет",
      "Судан",
      "Ливия",
      "Саудовская Аравия",
      "Иордания",
      "Ливан"
    ],
    "level": 4
  },
  {
    "question": "Версальский дворец",
    "answer": "Франция",
    "answers": [
      "Франция",
      "Бельгия",
      "Люксембург",
      "Нидерланды",
      "Германия",
      "Швейцария"
    ],
    "level": 4
  },
  {
    "question": "Гора Аконкагуа",
    "answer": "Аргентина",
    "answers": [
      "Аргентина",
      "Чили",
      "Перу",
      "Боливия",
      "Бразилия",
      "Уругвай"
    ],
    "level": 4
  }
]